atcu/__init__.py
atcu/hello.py
atcu/py.typed
atcu-0.1.0.dist-info/METADATA
atcu-0.1.0.dist-info/WHEEL
atcu-0.1.0.dist-info/licenses/LICENSE
atcu-0.1.0.dist-info/RECORD
