Metadata-Version: 2.4
Name: atcu
Version: 0.1.0
Summary: ATC Utils
Author-email: Alvin Yip <keongalvin@gmail.com>
License-Expression: MIT
License-File: LICENSE
Classifier: Development Status :: 3 - Alpha
Classifier: Intended Audience :: Developers
Classifier: License :: OSI Approved :: MIT License
Classifier: Programming Language :: Python :: 3.13
Requires-Python: >=3.13
